HashTools/__init__.py
HashTools/md5.py
HashTools/sha1.py
HashTools/sha224.py
HashTools/sha256.py
HashTools/sha384.py
HashTools/sha512.py
HashTools/utils.py
length_extension_tool-0.1.0.dist-info/METADATA
length_extension_tool-0.1.0.dist-info/WHEEL
length_extension_tool-0.1.0.dist-info/top_level.txt
length_extension_tool-0.1.0.dist-info/RECORD
