Metadata-Version: 2.1
Name: length-extension-tool
Version: 0.1.0
Summary: A pure python tool to implement/exploit the hash length extension attack
Home-page: https://github.com/viensea1106/hash-length-extension
Author: Nguyen Chuong Vo
Author-email: viensea1106@gmail.com
License: MIT
Keywords: hash length extension,md5,sha1,sha224,sha256,sha512
Classifier: Development Status :: 4 - Beta
Classifier: Intended Audience :: Education
Classifier: Topic :: Security
Classifier: Topic :: Security :: Cryptography
Classifier: License :: OSI Approved :: MIT License
Classifier: Programming Language :: Python :: 3
